{
  "GameTrans": {
    "EnterYourName": "Укажите ваше имя",
    "NameMax": "*Имя должно быть в пределах 15 символов.",
    "TAC": "*Условия и положения.",
    "Edit": "Редактировать",
    "CreateNew": "Создать заново",
    "Back": "Назад",
    "Next": "Далее",
    "Done": "Готово",
    "GearUpWith": "Приобретайте самые мощные материнские платы AORUS Z790 X",
    "UseItContent": "Используйте для своего профиля в социальных сетях",
    "Download": "Скачать",
    "ShareYourAORUS": "Поделиться своим AORUS Chibi",
    "Share": "Поделиться",
    "Twitter": "Twitter",
    "Facebook": "Facebook",
    "LongPressToSaveThePicture": "Нажмите и удерживайте чтобы сохранить изображение"
  },
  "Font": {
    "FontFamily": "@import url('https://fonts.googleapis.com/css2?family=Roboto:wght@300;500&display=swap');",
    "FontFamilyTag": "Roboto"
  }
}