{ "compressionlevel":-1,
 "height":10,
 "infinite":false,
 "layers":[
        {
         "data":[0, 0, 0, 0, 0, 0, 0, 0, 0, 0, 0, 0, 0, 0, 0,
            0, 1, 2, 3, 4, 5, 2, 2, 2, 2, 3, 4, 5, 6, 0,
            0, 8, 9, 10, 11, 12, 9, 9, 9, 9, 10, 11, 12, 13, 0,
            0, 15, 16, 17, 18, 19, 16, 17, 18, 19, 19, 19, 19, 13, 0,
            0, 8, 23, 24, 25, 26, 19, 18, 16, 17, 18, 19, 26, 13, 0,
            0, 15, 16, 16, 17, 18, 19, 17, 18, 19, 19, 19, 26, 13, 0,
            0, 8, 16, 16, 16, 17, 18, 19, 25, 26, 26, 26, 19, 13, 0,
            0, 15, 16, 23, 23, 24, 25, 26, 23, 16, 17, 18, 19, 20, 0,
            0, 22, 23, 24, 25, 23, 24, 23, 24, 23, 24, 25, 26, 27, 0,
            0, 29, 30, 31, 32, 33, 30, 31, 32, 30, 31, 32, 33, 34, 0],
         "height":10,
         "id":2,
         "name":"Map",
         "opacity":1,
         "type":"tilelayer",
         "visible":true,
         "width":15,
         "x":0,
         "y":0
        }, 
        {
         "data":[0, 0, 0, 0, 0, 0, 0, 0, 0, 0, 0, 0, 0, 0, 0,
            0, 0, 0, 0, 0, 0, 0, 0, 0, 0, 0, 0, 0, 0, 0,
            0, 0, 41, 0, 0, 0, 0, 42, 0, 0, 0, 0, 41, 0, 0,
            0, 0, 0, 0, 0, 0, 0, 0, 0, 0, 0, 0, 0, 0, 0,
            0, 0, 0, 0, 0, 0, 0, 0, 0, 0, 0, 0, 0, 0, 0,
            0, 0, 0, 0, 0, 0, 0, 0, 0, 0, 0, 0, 0, 0, 0,
            0, 0, 0, 0, 0, 0, 0, 0, 0, 0, 0, 0, 0, 0, 0,
            0, 0, 0, 0, 0, 0, 0, 0, 0, 0, 0, 0, 0, 0, 0,
            0, 0, 0, 0, 0, 0, 0, 0, 0, 0, 0, 0, 0, 0, 0,
            0, 0, 0, 0, 0, 0, 0, 0, 0, 0, 0, 0, 0, 0, 0],
         "height":10,
         "id":3,
         "name":"Object",
         "opacity":1,
         "type":"tilelayer",
         "visible":true,
         "width":15,
         "x":0,
         "y":0
        }, 
        {
         "data":[0, 0, 0, 0, 0, 0, 0, 0, 0, 0, 0, 0, 0, 0, 0,
            0, 0, 0, 0, 0, 0, 0, 0, 0, 0, 0, 0, 0, 0, 0,
            0, 0, 0, 0, 0, 0, 0, 35, 0, 0, 0, 0, 0, 0, 0,
            0, 0, 0, 0, 0, 0, 0, 0, 0, 0, 0, 0, 0, 0, 0,
            0, 0, 0, 0, 0, 0, 0, 0, 0, 0, 0, 0, 0, 0, 0,
            0, 0, 0, 0, 0, 0, 0, 0, 0, 0, 0, 0, 0, 0, 0,
            0, 0, 0, 0, 0, 0, 0, 0, 0, 0, 0, 0, 0, 0, 0,
            0, 0, 0, 0, 0, 0, 0, 0, 0, 0, 0, 0, 0, 0, 0,
            0, 0, 0, 0, 0, 0, 0, 0, 0, 0, 0, 0, 0, 0, 0,
            0, 0, 0, 0, 0, 0, 0, 0, 0, 0, 0, 0, 0, 0, 0],
         "height":10,
         "id":4,
         "name":"Object2",
         "opacity":1,
         "type":"tilelayer",
         "visible":true,
         "width":15,
         "x":0,
         "y":0
        }, 
        {
         "data":[0, 0, 0, 0, 0, 0, 0, 0, 0, 0, 0, 0, 0, 0, 0,
            0, 0, 0, 0, 0, 0, 0, 0, 0, 0, 0, 0, 0, 0, 0,
            0, 14, 14, 14, 14, 14, 14, 14, 14, 14, 14, 14, 14, 14, 0,
            0, 14, 0, 0, 0, 0, 0, 0, 0, 0, 0, 0, 0, 14, 0,
            0, 14, 0, 0, 0, 0, 0, 0, 0, 0, 0, 0, 0, 14, 0,
            0, 14, 0, 0, 0, 0, 0, 0, 0, 0, 0, 0, 0, 14, 0,
            0, 14, 0, 0, 0, 0, 0, 0, 0, 0, 0, 0, 0, 14, 0,
            0, 14, 0, 0, 0, 0, 0, 0, 0, 0, 0, 0, 0, 14, 0,
            0, 14, 0, 0, 0, 0, 0, 0, 0, 0, 0, 0, 0, 14, 0,
            0, 14, 14, 14, 14, 14, 14, 14, 14, 14, 14, 14, 14, 14, 0],
         "height":10,
         "id":1,
         "name":"Wall",
         "opacity":1,
         "type":"tilelayer",
         "visible":true,
         "width":15,
         "x":0,
         "y":0
        }, 
        {
         "draworder":"topdown",
         "id":5,
         "name":"BossAttack1",
         "objects":[
                {
                 "class":"",
                 "height":0,
                 "id":29,
                 "name":"",
                 "point":true,
                 "rotation":0,
                 "visible":true,
                 "width":0,
                 "x":96.5,
                 "y":128.5
                }, 
                {
                 "class":"",
                 "height":0,
                 "id":30,
                 "name":"",
                 "point":true,
                 "rotation":0,
                 "visible":true,
                 "width":0,
                 "x":97,
                 "y":159.5
                }, 
                {
                 "class":"",
                 "height":0,
                 "id":31,
                 "name":"",
                 "point":true,
                 "rotation":0,
                 "visible":true,
                 "width":0,
                 "x":95.5,
                 "y":192
                }, 
                {
                 "class":"",
                 "height":0,
                 "id":32,
                 "name":"",
                 "point":true,
                 "rotation":0,
                 "visible":true,
                 "width":0,
                 "x":96.5,
                 "y":224.5
                }, 
                {
                 "class":"",
                 "height":0,
                 "id":33,
                 "name":"",
                 "point":true,
                 "rotation":0,
                 "visible":true,
                 "width":0,
                 "x":96,
                 "y":256
                }, 
                {
                 "class":"",
                 "height":0,
                 "id":34,
                 "name":"",
                 "point":true,
                 "rotation":0,
                 "visible":true,
                 "width":0,
                 "x":128.5,
                 "y":254
                }, 
                {
                 "class":"",
                 "height":0,
                 "id":35,
                 "name":"",
                 "point":true,
                 "rotation":0,
                 "visible":true,
                 "width":0,
                 "x":128,
                 "y":225.5
                }, 
                {
                 "class":"",
                 "height":0,
                 "id":36,
                 "name":"",
                 "point":true,
                 "rotation":0,
                 "visible":true,
                 "width":0,
                 "x":128.5,
                 "y":192.5
                }, 
                {
                 "class":"",
                 "height":0,
                 "id":37,
                 "name":"",
                 "point":true,
                 "rotation":0,
                 "visible":true,
                 "width":0,
                 "x":129,
                 "y":128
                }, 
                {
                 "class":"",
                 "height":0,
                 "id":38,
                 "name":"",
                 "point":true,
                 "rotation":0,
                 "visible":true,
                 "width":0,
                 "x":128.5,
                 "y":159.5
                }, 
                {
                 "class":"",
                 "height":0,
                 "id":39,
                 "name":"",
                 "point":true,
                 "rotation":0,
                 "visible":true,
                 "width":0,
                 "x":160.5,
                 "y":128
                }, 
                {
                 "class":"",
                 "height":0,
                 "id":40,
                 "name":"",
                 "point":true,
                 "rotation":0,
                 "visible":true,
                 "width":0,
                 "x":192.5,
                 "y":129
                }, 
                {
                 "class":"",
                 "height":0,
                 "id":41,
                 "name":"",
                 "point":true,
                 "rotation":0,
                 "visible":true,
                 "width":0,
                 "x":224,
                 "y":128
                }, 
                {
                 "class":"",
                 "height":0,
                 "id":42,
                 "name":"",
                 "point":true,
                 "rotation":0,
                 "visible":true,
                 "width":0,
                 "x":256,
                 "y":127.5
                }, 
                {
                 "class":"",
                 "height":0,
                 "id":43,
                 "name":"",
                 "point":true,
                 "rotation":0,
                 "visible":true,
                 "width":0,
                 "x":288,
                 "y":126.5
                },
            
                {
                 "class":"",
                 "height":0,
                 "id":44,
                 "name":"",
                 "point":true,
                 "rotation":0,
                 "visible":true,
                 "width":0,
                 "x":319.5,
                 "y":126
                }, 
                {
                 "class":"",
                 "height":0,
                 "id":45,
                 "name":"",
                 "point":true,
                 "rotation":0,
                 "visible":true,
                 "width":0,
                 "x":351.5,
                 "y":127.5
                }, 
                {
                 "class":"",
                 "height":0,
                 "id":46,
                 "name":"",
                 "point":true,
                 "rotation":0,
                 "visible":true,
                 "width":0,
                 "x":383.5,
                 "y":127
                }, 
                {
                 "class":"",
                 "height":0,
                 "id":47,
                 "name":"",
                 "point":true,
                 "rotation":0,
                 "visible":true,
                 "width":0,
                 "x":160,
                 "y":160
                }, 
                {
                 "class":"",
                 "height":0,
                 "id":48,
                 "name":"",
                 "point":true,
                 "rotation":0,
                 "visible":true,
                 "width":0,
                 "x":192.5,
                 "y":159
                }, 
                {
                 "class":"",
                 "height":0,
                 "id":49,
                 "name":"",
                 "point":true,
                 "rotation":0,
                 "visible":true,
                 "width":0,
                 "x":224,
                 "y":159
                }, 
                {
                 "class":"",
                 "height":0,
                 "id":50,
                 "name":"",
                 "point":true,
                 "rotation":0,
                 "visible":true,
                 "width":0,
                 "x":257,
                 "y":160
                }, 
                {
                 "class":"",
                 "height":0,
                 "id":51,
                 "name":"",
                 "point":true,
                 "rotation":0,
                 "visible":true,
                 "width":0,
                 "x":288,
                 "y":159.5
                }, 
                {
                 "class":"",
                 "height":0,
                 "id":52,
                 "name":"",
                 "point":true,
                 "rotation":0,
                 "visible":true,
                 "width":0,
                 "x":319.5,
                 "y":159.5
                }, 
                {
                 "class":"",
                 "height":0,
                 "id":53,
                 "name":"",
                 "point":true,
                 "rotation":0,
                 "visible":true,
                 "width":0,
                 "x":352,
                 "y":159.5
                }, 
                {
                 "class":"",
                 "height":0,
                 "id":54,
                 "name":"",
                 "point":true,
                 "rotation":0,
                 "visible":true,
                 "width":0,
                 "x":383.5,
                 "y":159
                }, 
                {
                 "class":"",
                 "height":0,
                 "id":55,
                 "name":"",
                 "point":true,
                 "rotation":0,
                 "visible":true,
                 "width":0,
                 "x":160,
                 "y":192.5
                }, 
                {
                 "class":"",
                 "height":0,
                 "id":56,
                 "name":"",
                 "point":true,
                 "rotation":0,
                 "visible":true,
                 "width":0,
                 "x":160,
                 "y":224
                }, 
                {
                 "class":"",
                 "height":0,
                 "id":57,
                 "name":"",
                 "point":true,
                 "rotation":0,
                 "visible":true,
                 "width":0,
                 "x":160.5,
                 "y":255.5
                }, 
                {
                 "class":"",
                 "height":0,
                 "id":58,
                 "name":"",
                 "point":true,
                 "rotation":0,
                 "visible":true,
                 "width":0,
                 "x":192,
                 "y":256.5
                },
            
                {
                 "class":"",
                 "height":0,
                 "id":59,
                 "name":"",
                 "point":true,
                 "rotation":0,
                 "visible":true,
                 "width":0,
                 "x":225,
                 "y":256
                }, 
                {
                 "class":"",
                 "height":0,
                 "id":60,
                 "name":"",
                 "point":true,
                 "rotation":0,
                 "visible":true,
                 "width":0,
                 "x":255.5,
                 "y":255
                }, 
                {
                 "class":"",
                 "height":0,
                 "id":61,
                 "name":"",
                 "point":true,
                 "rotation":0,
                 "visible":true,
                 "width":0,
                 "x":288,
                 "y":256.5
                }, 
                {
                 "class":"",
                 "height":0,
                 "id":62,
                 "name":"",
                 "point":true,
                 "rotation":0,
                 "visible":true,
                 "width":0,
                 "x":319.5,
                 "y":256
                }, 
                {
                 "class":"",
                 "height":0,
                 "id":63,
                 "name":"",
                 "point":true,
                 "rotation":0,
                 "visible":true,
                 "width":0,
                 "x":353,
                 "y":255
                }, 
                {
                 "class":"",
                 "height":0,
                 "id":64,
                 "name":"",
                 "point":true,
                 "rotation":0,
                 "visible":true,
                 "width":0,
                 "x":386,
                 "y":255.5
                }, 
                {
                 "class":"",
                 "height":0,
                 "id":65,
                 "name":"",
                 "point":true,
                 "rotation":0,
                 "visible":true,
                 "width":0,
                 "x":384.5,
                 "y":224
                }, 
                {
                 "class":"",
                 "height":0,
                 "id":66,
                 "name":"",
                 "point":true,
                 "rotation":0,
                 "visible":true,
                 "width":0,
                 "x":385,
                 "y":191.5
                }, 
                {
                 "class":"",
                 "height":0,
                 "id":67,
                 "name":"",
                 "point":true,
                 "rotation":0,
                 "visible":true,
                 "width":0,
                 "x":351.5,
                 "y":192.5
                }, 
                {
                 "class":"",
                 "height":0,
                 "id":68,
                 "name":"",
                 "point":true,
                 "rotation":0,
                 "visible":true,
                 "width":0,
                 "x":352.5,
                 "y":223.5
                }, 
                {
                 "class":"",
                 "height":0,
                 "id":69,
                 "name":"",
                 "point":true,
                 "rotation":0,
                 "visible":true,
                 "width":0,
                 "x":319.5,
                 "y":222.5
                }, 
                {
                 "class":"",
                 "height":0,
                 "id":70,
                 "name":"",
                 "point":true,
                 "rotation":0,
                 "visible":true,
                 "width":0,
                 "x":319.5,
                 "y":193
                }, 
                {
                 "class":"",
                 "height":0,
                 "id":71,
                 "name":"",
                 "point":true,
                 "rotation":0,
                 "visible":true,
                 "width":0,
                 "x":289,
                 "y":191
                }, 
                {
                 "class":"",
                 "height":0,
                 "id":72,
                 "name":"",
                 "point":true,
                 "rotation":0,
                 "visible":true,
                 "width":0,
                 "x":287,
                 "y":225
                }, 
                {
                 "class":"",
                 "height":0,
                 "id":73,
                 "name":"",
                 "point":true,
                 "rotation":0,
                 "visible":true,
                 "width":0,
                 "x":256,
                 "y":225
                },
            
                {
                 "class":"",
                 "height":0,
                 "id":74,
                 "name":"",
                 "point":true,
                 "rotation":0,
                 "visible":true,
                 "width":0,
                 "x":256.5,
                 "y":192.5
                }, 
                {
                 "class":"",
                 "height":0,
                 "id":75,
                 "name":"",
                 "point":true,
                 "rotation":0,
                 "visible":true,
                 "width":0,
                 "x":223.5,
                 "y":192
                }, 
                {
                 "class":"",
                 "height":0,
                 "id":76,
                 "name":"",
                 "point":true,
                 "rotation":0,
                 "visible":true,
                 "width":0,
                 "x":223.5,
                 "y":224
                }, 
                {
                 "class":"",
                 "height":0,
                 "id":77,
                 "name":"",
                 "point":true,
                 "rotation":0,
                 "visible":true,
                 "width":0,
                 "x":191.5,
                 "y":223.5
                }, 
                {
                 "class":"",
                 "height":0,
                 "id":128,
                 "name":"",
                 "point":true,
                 "rotation":0,
                 "visible":true,
                 "width":0,
                 "x":192,
                 "y":191.5
                }],
         "opacity":1,
         "type":"objectgroup",
         "visible":false,
         "x":0,
         "y":0
        }, 
        {
         "draworder":"topdown",
         "id":10,
         "name":"BossAttack2",
         "objects":[
                {
                 "class":"",
                 "height":0,
                 "id":183,
                 "name":"",
                 "point":true,
                 "rotation":0,
                 "visible":true,
                 "width":0,
                 "x":112.333333333333,
                 "y":144.333333333333
                }, 
                {
                 "class":"",
                 "height":0,
                 "id":184,
                 "name":"",
                 "point":true,
                 "rotation":0,
                 "visible":true,
                 "width":0,
                 "x":112,
                 "y":240.333333333333
                }, 
                {
                 "class":"",
                 "height":0,
                 "id":185,
                 "name":"",
                 "point":true,
                 "rotation":0,
                 "visible":true,
                 "width":0,
                 "x":368,
                 "y":143.666666666667
                }, 
                {
                 "class":"",
                 "height":0,
                 "id":186,
                 "name":"",
                 "point":true,
                 "rotation":0,
                 "visible":true,
                 "width":0,
                 "x":367.333333333333,
                 "y":240.666666666667
                }, 
                {
                 "class":"",
                 "height":0,
                 "id":187,
                 "name":"",
                 "point":true,
                 "rotation":0,
                 "visible":true,
                 "width":0,
                 "x":191.666666666667,
                 "y":191
                }, 
                {
                 "class":"",
                 "height":0,
                 "id":188,
                 "name":"",
                 "point":true,
                 "rotation":0,
                 "visible":true,
                 "width":0,
                 "x":288,
                 "y":191.666666666667
                }, 
                {
                 "class":"",
                 "height":0,
                 "id":189,
                 "name":"",
                 "point":true,
                 "rotation":0,
                 "visible":true,
                 "width":0,
                 "x":239.666666666667,
                 "y":256.666666666667
                }, 
                {
                 "class":"",
                 "height":0,
                 "id":190,
                 "name":"",
                 "point":true,
                 "rotation":0,
                 "visible":true,
                 "width":0,
                 "x":239,
                 "y":128
                }],
         "opacity":1,
         "type":"objectgroup",
         "visible":true,
         "x":0,
         "y":0
        }],
 "nextlayerid":11,
 "nextobjectid":191,
 "orientation":"orthogonal",
 "renderorder":"right-down",
 "tiledversion":"1.9.2",
 "tileheight":32,
 "tilesets":[
        {
         "columns":7,
         "firstgid":1,
         "image":"..\/images\/Full.png",
         "imageheight":256,
         "imagewidth":224,
         "margin":0,
         "name":"Full",
         "spacing":0,
         "tilecount":56,
         "tileheight":32,
         "tiles":[
                {
                 "id":27,
                 "properties":[
                        {
                         "name":"name",
                         "type":"string",
                         "value":"DoorLock"
                        }]
                }, 
                {
                 "id":34,
                 "properties":[
                        {
                         "name":"name",
                         "type":"string",
                         "value":"DoorOpen"
                        }]
                }, 
                {
                 "id":41,
                 "properties":[
                        {
                         "name":"name",
                         "type":"string",
                         "value":"DoorColse"
                        }]
                }],
         "tilewidth":32,
         "transparentcolor":"#ff00ff"
        }],
 "tilewidth":32,
 "type":"map",
 "version":"1.9",
 "width":15
}